fimdpenv/AEVEnv.py
fimdpenv/UUVEnv.py
fimdpenv/__init__.py
fimdpenv-1.0.4.dist-info/LICENSE
fimdpenv-1.0.4.dist-info/METADATA
fimdpenv-1.0.4.dist-info/WHEEL
fimdpenv-1.0.4.dist-info/top_level.txt
fimdpenv-1.0.4.dist-info/RECORD
