Metadata-Version: 2.1
Name: fimdpenv
Version: 1.0.4
Summary: Simulation environments for FiMDP
Home-page: https://github.com/FiMDP/FiMDPEnv
Author: Pranay Thangeda
Author-email: contact@prny.me
License: MIT
Keywords: simulation-environment,grid-world,agent,cmdp,uuv-dynamics,street-network,formal-methods
Platform: UNKNOWN
Requires-Python: >=3.6.0
Requires-Dist: fimdp (>=2.0.0)
Requires-Dist: numpy (>=1.18.5)
Requires-Dist: matplotlib (>=3.2.2)
Requires-Dist: scipy (>=1.5.0)
Requires-Dist: ipython (>=7.16.1)
Requires-Dist: networkx (>=2.5)
Requires-Dist: folium (>=0.11.0)
